eledubby/__init__.py
eledubby/__main__.py
eledubby/_version.py
eledubby/config.toml
eledubby/eledubby.py
eledubby/api/__init__.py
eledubby/api/elevenlabs_client.py
eledubby/audio/__init__.py
eledubby/audio/analyzer.py
eledubby/audio/extractor.py
eledubby/audio/processor.py
eledubby/audio/segmenter.py
eledubby/utils/__init__.py
eledubby/utils/progress.py
eledubby/utils/temp_manager.py
eledubby/video/__init__.py
eledubby/video/remuxer.py
eledubby-1.0.5.dist-info/METADATA
eledubby-1.0.5.dist-info/WHEEL
eledubby-1.0.5.dist-info/entry_points.txt
eledubby-1.0.5.dist-info/licenses/LICENSE
eledubby-1.0.5.dist-info/RECORD
