Metadata-Version: 2.4
Name: eledubby
Version: 1.0.5
Summary: Voice dubbing tool using ElevenLabs API for speech-to-speech conversion
Project-URL: Homepage, https://github.com/twardoch/eledubby
Project-URL: Documentation, https://github.com/twardoch/eledubby#readme
Project-URL: Repository, https://github.com/twardoch/eledubby
Project-URL: Issues, https://github.com/twardoch/eledubby/issues
Author-email: Adam Twardoch <adam+github@twardoch.com>
License-Expression: MIT
License-File: LICENSE
Classifier: Development Status :: 4 - Beta
Classifier: Intended Audience :: Developers
Classifier: Intended Audience :: End Users/Desktop
Classifier: License :: OSI Approved :: MIT License
Classifier: Operating System :: OS Independent
Classifier: Programming Language :: Python :: 3
Classifier: Programming Language :: Python :: 3.8
Classifier: Programming Language :: Python :: 3.9
Classifier: Programming Language :: Python :: 3.10
Classifier: Programming Language :: Python :: 3.11
Classifier: Programming Language :: Python :: 3.12
Classifier: Topic :: Multimedia :: Sound/Audio :: Speech
Classifier: Topic :: Multimedia :: Video :: Conversion
Requires-Python: >=3.12
Requires-Dist: elevenlabs>=2.8.1
Requires-Dist: fire>=0.7.0
Requires-Dist: loguru>=0.7.0
Requires-Dist: numpy>=2.3.2
Requires-Dist: pedalboard>=0.9.0
Requires-Dist: python-dotenv>=1.0.0
Requires-Dist: rich>=14.1.0
Requires-Dist: scipy>=1.7.0
Requires-Dist: toml>=0.10.2
